faas_client/__init__.py
faas_client/faas_client.py
faas_client-1.4.23.dist-info/METADATA
faas_client-1.4.23.dist-info/WHEEL
faas_client-1.4.23.dist-info/top_level.txt
faas_client-1.4.23.dist-info/RECORD
