Metadata-Version: 2.1
Name: faas-client
Version: 1.4.23
Summary: A client library for faas-cli
Home-page: https://gitlab.hidora.com/softozor/packages
Author: Laurent Michel
Author-email: softozor@gmail.com
License: UNKNOWN
Platform: UNKNOWN
Classifier: Programming Language :: Python :: 3.9
Classifier: License :: OSI Approved :: MIT License
Classifier: Operating System :: OS Independent
Requires-Python: >=3.9
Requires-Dist: sh
Provides-Extra: test
Requires-Dist: pytest ; extra == 'test'
Requires-Dist: pytest-xdist ; extra == 'test'
